pyrobotstxt/__init__.py
pyrobotstxt-0.0.5.dist-info/LICENSE
pyrobotstxt-0.0.5.dist-info/METADATA
pyrobotstxt-0.0.5.dist-info/WHEEL
pyrobotstxt-0.0.5.dist-info/top_level.txt
pyrobotstxt-0.0.5.dist-info/RECORD
